bintropy/VERSION.txt
bintropy/__info__.py
bintropy/__init__.py
bintropy/__main__.py
bintropy-1.5.7.dist-info/LICENSE
bintropy-1.5.7.dist-info/METADATA
bintropy-1.5.7.dist-info/WHEEL
bintropy-1.5.7.dist-info/entry_points.txt
bintropy-1.5.7.dist-info/top_level.txt
bintropy-1.5.7.dist-info/RECORD
