Metadata-Version: 2.1
Name: bintropy
Version: 1.5.7
Summary: Analysis tool for estimating the likelihood that a binary contains compressed or encrypted bytes
Author-email: Alexandre D'Hondt <alexandre.dhondt@gmail.com>
License: GNU GENERAL PUBLIC LICENSE
Project-URL: homepage, https://github.com/packing-box/bintropy
Project-URL: issues, https://github.com/packing-box/bintropy/issues
Project-URL: repository, https://github.com/packing-box/bintropy
Keywords: binary,entropy,bintropy,packing,packed-executable,packing-detection,elf,pe
Classifier: Development Status :: 5 - Production/Stable
Classifier: Environment :: Console
Classifier: Intended Audience :: Developers
Classifier: Intended Audience :: Information Technology
Classifier: Intended Audience :: Other Audience
Classifier: License :: OSI Approved :: GNU General Public License v3 or later (GPLv3+)
Classifier: Programming Language :: Python :: 3
Classifier: Programming Language :: Python :: 3 :: Only
Classifier: Programming Language :: Python :: 3.8
Classifier: Programming Language :: Python :: 3.9
Classifier: Programming Language :: Python :: 3.10
Classifier: Programming Language :: Python :: 3.11
Classifier: Topic :: Software Development :: Libraries :: Python Modules
Classifier: Topic :: Security
Requires-Python: <4,>=3.8
License-File: LICENSE
Requires-Dist: fonttools >=4.43.0
Requires-Dist: lief >=0.14.0
Requires-Dist: matplotlib >=3.7.4
Requires-Dist: numpy >=1.23.0
Requires-Dist: pillow >=10.0.1
